<?xml version="1.0" encoding="iso-8859-1"?>
<!--
     The FreeBSD Documentation Project

     $FreeBSD$
-->
<informaltable frame="none" pgwide="1">
  <tgroup cols="3">
    <colspec colwidth="40%"/>
    <colspec colwidth="30%"/>
    <colspec colwidth="30%"/>
    <thead>
      <row>
	<entry>Errata</entry>
	<entry>Date</entry>
	<entry>Topic</entry>
      </row>
    </thead>

    <tbody>
      <row>
	<entry><link
	    xlink:href="&security.url;/FreeBSD-EN-19:19.loader.asc">FreeBSD-EN-19:19.loader</link></entry>
	<entry>12&nbsp;November&nbsp;2019</entry>
	<entry><para>UEFI Loader Memory Fragmentation</para></entry>
      </row>

      <row>
	<entry><link
	    xlink:href="&security.url;/FreeBSD-EN-20:01.ssp.asc">FreeBSD-EN-20:01.ssp</link></entry>
	<entry>28&nbsp;January&nbsp;2020</entry>
	<entry><para>Imprecise orderring of canary
	  initialization</para></entry>
      </row>

      <row>
	<entry><link
	    xlink:href="&security.url;/FreeBSD-EN-20:03.sshd.asc">FreeBSD-EN-20:03.sshd</link></entry>
	<entry>18&nbsp;March&nbsp;2020</entry>
	<entry><para>Misleading log messages upon successful
	  login</para></entry>
      </row>

      <row>
	<entry><link
	    xlink:href="&security.url;/FreeBSD-EN-20:05.mlx5en.asc">FreeBSD-EN-20:05.mlx5en</link></entry>
	<entry>18&nbsp;March&nbsp;2020</entry>
	<entry><para>Fix packet forwarding performance</para></entry>
      </row>

      <row>
	<entry><link
	    xlink:href="&security.url;/FreeBSD-EN-20:06.ipv6.asc">FreeBSD-EN-20:06.ipv6</link></entry>
	<entry>18&nbsp;March&nbsp;2020</entry>
	<entry><para>Incorrect checksum calculations</para></entry>
      </row>

      <row>
	<entry><link
	    xlink:href="&security.url;/FreeBSD-EN-20:07.quotad.asc">FreeBSD-EN-20:07.quotad</link></entry>
	<entry>21&nbsp;April&nbsp;2020</entry>
	<entry><para>Regression with certain <acronym>NFS</acronym>
	  servers</para></entry>
      </row>
    </tbody>
  </tgroup>
</informaltable>
