<?xml version="1.0" encoding="iso-8859-1"?>
<!--
     The FreeBSD Documentation Project

     $FreeBSD$
-->
<informaltable frame="none" pgwide="1">
  <tgroup cols="3">
    <colspec colwidth="40%"/>
    <colspec colwidth="30%"/>
    <colspec colwidth="30%"/>
    <thead>
      <row>
	<entry>Errata</entry>
	<entry>Date</entry>
	<entry>Topic</entry>
      </row>
    </thead>

    <tbody>
      <row>
	<entry><link
	    xlink:href="&security.url;/FreeBSD-EN-19:19.loader.asc">FreeBSD-EN-19:19.loader</link></entry>
	<entry>12&nbsp;November&nbsp;2019</entry>
	<entry><para>UEFI Loader Memory Fragmentation</para></entry>
      </row>

      <row>
	<entry><link
	    xlink:href="&security.url;/FreeBSD-EN-20:01.ssp.asc">FreeBSD-EN-20:01.ssp</link></entry>
	<entry>28&nbsp;January&nbsp;2020</entry>
	<entry><para>Imprecise orderring of canary
	  initialization</para></entry>
      </row>
    </tbody>
  </tgroup>
</informaltable>
