<?xml version="1.0" encoding="utf-8"?>
<!--
     The FreeBSD Mongolian Documentation Project

     Original revision 39297

     $FreeBSD$
-->
<!--

  Do not edit this file except as instructed by the addkey.sh script.

  See the README file in head/share/pgpkeys for instructions.

-->
<appendix id="pgpkeys">
  <title>PGP түлхүүрүүд</title>

  <indexterm><primary>pgp түлхүүрүүд</primary></indexterm>
  <para>Албан хаагчид эсвэл хөгжүүлэгчдийн аль нэгний гарын үсгийг шалгах эсвэл
	тэдэнд шифрлэсэн цахим захидал илгээх хэрэг гарах үед таны ая туханд
	зориулан хэд хэдэн түлхүүрүүдийг энд тавив.
	<hostid role="domainname">FreeBSD.org</hostid>-ийн
	хэрэглэгчдийн бүрэн гүйцэд түлхүүрүүдийг
	<ulink url="&url.base;/doc/pgpkeyring.txt">http://www.FreeBSD.org/doc/pgpkeyring.txt</ulink>
	хаягаас татаж авах боломжтой.</para>

  <sect1 id="pgpkeys-officers">
    <title>Албан хаагчид</title>

    &section.pgpkeys-officers;
  </sect1>

  <sect1 id="pgpkeys-core">
    <title>Гол багийн гишүүд</title>

    &section.pgpkeys-core;
  </sect1>

  <sect1 id="pgpkeys-developers">
    <title>Хөгжүүлэгчид</title>

    &section.pgpkeys-developers;
  </sect1>
</appendix>
